EditorMDiv/__init__.py
EditorMDiv/__main__.py
EditorMDiv/src/__init__.py
EditorMDiv/src/app.py
EditorMDiv/src/arg_handler.py
EditorMDiv/src/file_handler.py
EditorMDiv/src/utils.py
EditorMDiv-0.1.dist-info/METADATA
EditorMDiv-0.1.dist-info/WHEEL
EditorMDiv-0.1.dist-info/entry_points.txt
EditorMDiv-0.1.dist-info/top_level.txt
EditorMDiv-0.1.dist-info/RECORD
