Metadata-Version: 2.1
Name: EditorMDiv
Version: 0.1
Summary: UNKNOWN
Home-page: UNKNOWN
License: UNKNOWN
Platform: UNKNOWN
Requires-Dist: Jinja2 ==3.1.3
Requires-Dist: MarkupSafe ==2.1.4
Requires-Dist: PyYAML ==6.0.1
Requires-Dist: Pygments ==2.17.2
Requires-Dist: anyio ==4.2.0
Requires-Dist: arrow ==1.3.0
Requires-Dist: binaryornot ==0.4.4
Requires-Dist: certifi ==2023.11.17
Requires-Dist: chardet ==5.2.0
Requires-Dist: charset-normalizer ==3.3.2
Requires-Dist: click ==8.1.7
Requires-Dist: cookiecutter ==2.5.0
Requires-Dist: exceptiongroup ==1.2.0
Requires-Dist: flet-core ==0.19.0
Requires-Dist: flet-runtime ==0.19.0
Requires-Dist: flet ==0.19.0
Requires-Dist: h11 ==0.14.0
Requires-Dist: httpcore ==0.17.3
Requires-Dist: httpx ==0.24.1
Requires-Dist: idna ==3.6
Requires-Dist: markdown-it-py ==3.0.0
Requires-Dist: mdurl ==0.1.2
Requires-Dist: oauthlib ==3.2.2
Requires-Dist: packaging ==23.2
Requires-Dist: pypng ==0.20220715.0
Requires-Dist: python-dateutil ==2.8.2
Requires-Dist: python-slugify ==8.0.2
Requires-Dist: qrcode ==7.4.2
Requires-Dist: repath ==0.9.0
Requires-Dist: requests ==2.31.0
Requires-Dist: rich ==13.7.0
Requires-Dist: six ==1.16.0
Requires-Dist: sniffio ==1.3.0
Requires-Dist: text-unidecode ==1.3
Requires-Dist: types-python-dateutil ==2.8.19.20240106
Requires-Dist: typing-extensions ==4.9.0
Requires-Dist: urllib3 ==2.1.0
Requires-Dist: watchdog ==3.0.0
Requires-Dist: websocket-client ==1.7.0
Requires-Dist: websockets ==11.0.3
